paqueteoptimizacionelizabethrm/__init__.py
paqueteoptimizacionelizabethrm/funciones/__init__.py
paqueteoptimizacionelizabethrm/funciones/funcionesobjetivo.py
paqueteoptimizacionelizabethrm/multivariable/__init__.py
paqueteoptimizacionelizabethrm/multivariable/metodosdirectos/__init__.py
paqueteoptimizacionelizabethrm/multivariable/metodosdirectos/colina.py
paqueteoptimizacionelizabethrm/multivariable/metodosdirectos/hookejeeves.py
paqueteoptimizacionelizabethrm/multivariable/metodosdirectos/neldermeadsimplex.py
paqueteoptimizacionelizabethrm/multivariable/metodosdirectos/randomwalk.py
paqueteoptimizacionelizabethrm/multivariable/metodosdirectos/recocido.py
paqueteoptimizacionelizabethrm/multivariable/metodosgradiente/__init__.py
paqueteoptimizacionelizabethrm/multivariable/metodosgradiente/cauchy.py
paqueteoptimizacionelizabethrm/multivariable/metodosgradiente/gradienteconjugado.py
paqueteoptimizacionelizabethrm/multivariable/metodosgradiente/newton.py
paqueteoptimizacionelizabethrm/univariable/__init__.py
paqueteoptimizacionelizabethrm/univariable/metodosbasadosenladerivada/__init__.py
paqueteoptimizacionelizabethrm/univariable/metodosbasadosenladerivada/biseccion.py
paqueteoptimizacionelizabethrm/univariable/metodosbasadosenladerivada/newton.py
paqueteoptimizacionelizabethrm/univariable/metodosbasadosenladerivada/secante.py
paqueteoptimizacionelizabethrm/univariable/metodoseliminacionderegiones/__init__.py
paqueteoptimizacionelizabethrm/univariable/metodoseliminacionderegiones/bounding.py
paqueteoptimizacionelizabethrm/univariable/metodoseliminacionderegiones/exhaustiva.py
paqueteoptimizacionelizabethrm/univariable/metodoseliminacionderegiones/fibonacci.py
paqueteoptimizacionelizabethrm/univariable/metodoseliminacionderegiones/golden.py
paqueteoptimizacionelizabethrm/univariable/metodoseliminacionderegiones/intervalhalving.py
paqueteoptimizacionelizabethrm/utils/__init__.py
paqueteoptimizacionelizabethrm/utils/graficas.py
paqueteoptimizacionelizabethrm-0.1.0.dist-info/METADATA
paqueteoptimizacionelizabethrm-0.1.0.dist-info/WHEEL
paqueteoptimizacionelizabethrm-0.1.0.dist-info/top_level.txt
paqueteoptimizacionelizabethrm-0.1.0.dist-info/RECORD
