Metadata-Version: 2.1
Name: paqueteoptimizacionelizabethrm
Version: 0.1.0
Summary: Métodos de optimización
Author: Eli
Author-email: tuemail@email.com
Keywords: Python,optimización,funciones,gráficas
Classifier: Development Status :: 3 - Alpha
Classifier: Intended Audience :: Education
Classifier: Programming Language :: Python :: 3
Classifier: Operating System :: OS Independent
Classifier: Operating System :: MacOS :: MacOS X
Classifier: Operating System :: Microsoft :: Windows
Requires-Python: >=3.6
Requires-Dist: numpy
Requires-Dist: matplotlib
